odoo/addons/asterisk_click2dial/README.rst
odoo/addons/asterisk_click2dial/__init__.py
odoo/addons/asterisk_click2dial/__manifest__.py
odoo/addons/asterisk_click2dial/controller.py
odoo/addons/asterisk_click2dial/requirements.txt
odoo/addons/asterisk_click2dial/demo/asterisk_click2dial_demo.xml
odoo/addons/asterisk_click2dial/i18n/am.po
odoo/addons/asterisk_click2dial/i18n/asterisk_click2dial.pot
odoo/addons/asterisk_click2dial/i18n/bg.po
odoo/addons/asterisk_click2dial/i18n/ca.po
odoo/addons/asterisk_click2dial/i18n/de.po
odoo/addons/asterisk_click2dial/i18n/el_GR.po
odoo/addons/asterisk_click2dial/i18n/es.po
odoo/addons/asterisk_click2dial/i18n/es_AR.po
odoo/addons/asterisk_click2dial/i18n/es_ES.po
odoo/addons/asterisk_click2dial/i18n/fi.po
odoo/addons/asterisk_click2dial/i18n/fr.po
odoo/addons/asterisk_click2dial/i18n/gl.po
odoo/addons/asterisk_click2dial/i18n/hr.po
odoo/addons/asterisk_click2dial/i18n/it.po
odoo/addons/asterisk_click2dial/i18n/nl_BE.po
odoo/addons/asterisk_click2dial/i18n/pt.po
odoo/addons/asterisk_click2dial/i18n/pt_BR.po
odoo/addons/asterisk_click2dial/i18n/pt_PT.po
odoo/addons/asterisk_click2dial/i18n/sl.po
odoo/addons/asterisk_click2dial/i18n/tr.po
odoo/addons/asterisk_click2dial/models/__init__.py
odoo/addons/asterisk_click2dial/models/asterisk_server.py
odoo/addons/asterisk_click2dial/models/phone_common.py
odoo/addons/asterisk_click2dial/models/res_users.py
odoo/addons/asterisk_click2dial/readme/CONTRIBUTORS.md
odoo/addons/asterisk_click2dial/readme/DESCRIPTION.md
odoo/addons/asterisk_click2dial/scripts/odoo_popup_timeout.sh
odoo/addons/asterisk_click2dial/scripts/set_name_agi.py
odoo/addons/asterisk_click2dial/scripts/set_name_incoming_timeout.sh
odoo/addons/asterisk_click2dial/scripts/set_name_outgoing_timeout.sh
odoo/addons/asterisk_click2dial/security/asterisk_security.xml
odoo/addons/asterisk_click2dial/security/ir.model.access.csv
odoo/addons/asterisk_click2dial/static/description/icon.png
odoo_addon_asterisk_click2dial-17.0.1.0.0.6.dist-info/METADATA
odoo_addon_asterisk_click2dial-17.0.1.0.0.6.dist-info/WHEEL
odoo_addon_asterisk_click2dial-17.0.1.0.0.6.dist-info/top_level.txt
odoo_addon_asterisk_click2dial-17.0.1.0.0.6.dist-info/RECORD
